show/__init__.py
show/core.py
show/exceptions.py
show/introspect.py
show/linecacher.py
show/pretty.py
show/termsize.py
show/util.py
show/version.py
show/astor/__init__.py
show/astor/code_gen.py
show/astor/file_util.py
show/astor/node_util.py
show/astor/op_util.py
show/astor/rtrip.py
show/astor/source_repr.py
show/astor/string_repr.py
show/astor/tree_walk.py
show-1.6.0.dist-info/DESCRIPTION.rst
show-1.6.0.dist-info/METADATA
show-1.6.0.dist-info/RECORD
show-1.6.0.dist-info/WHEEL
show-1.6.0.dist-info/metadata.json
show-1.6.0.dist-info/top_level.txt
