Metadata-Version: 2.0
Name: show
Version: 1.6.0
Summary: Debug print statements, done right. E.g. show(x)
Home-page: https://bitbucket.org/jeunice/show
Author: Jonathan Eunice
Author-email: jonathan.eunice@gmail.com
License: Apache License 2.0
Keywords: debug print display show
Platform: UNKNOWN
Classifier: Development Status :: 4 - Beta
Classifier: Operating System :: OS Independent
Classifier: License :: OSI Approved :: Apache Software License
Classifier: Intended Audience :: Developers
Classifier: Programming Language :: Python
Classifier: Programming Language :: Python :: 2
Classifier: Programming Language :: Python :: 2.6
Classifier: Programming Language :: Python :: 2.7
Classifier: Programming Language :: Python :: 3
Classifier: Programming Language :: Python :: 3.3
Classifier: Programming Language :: Python :: 3.4
Classifier: Programming Language :: Python :: 3.5
Classifier: Programming Language :: Python :: 3.6
Classifier: Programming Language :: Python :: Implementation :: CPython
Classifier: Programming Language :: Python :: Implementation :: PyPy
Classifier: Framework :: IPython
Classifier: Environment :: Console
Classifier: Topic :: Software Development :: Libraries :: Python Modules
Classifier: Topic :: Printing
Classifier: Topic :: Software Development :: Debuggers
Requires-Dist: ipython
Requires-Dist: mementos (>=1.2.5)
Requires-Dist: options (>=1.4.6)
Requires-Dist: pygments (>=2.2.0)
Requires-Dist: readline
Requires-Dist: say (>=1.5.0)
Requires-Dist: six (>=1.10)
Requires-Dist: textdata
